[[{"__type__":"cc.SceneAsset","_name":"welcom","scene":{"__id__":1},"asyncLoadAssets":null},{"__type__":"cc.Scene","_name":"New Node","_children":[{"__id__":2}],"_anchorPoint":{"__type__":"cc.Vec2"},"autoReleaseAssets":false},{"__type__":"cc.Node","_name":"Canvas","_parent":{"__id__":1},"_children":[{"__id__":3},{"__id__":4}],"_components":[{"__type__":"cc.Canvas","node":{"__id__":2},"_designResolution":{"__type__":"cc.Size","width":640,"height":960},"_fitWidth":true},{"__type__":"46eb0RAZExKtbqV79sCxT+6","node":{"__id__":2},"btnStart":{"__id__":6}}],"_id":"6aPWh40oJMfa88PGimCRwf","_contentSize":{"__type__":"cc.Size","width":640,"height":960},"_position":{"__type__":"cc.Vec2","x":320,"y":480}},{"__type__":"cc.Node","_name":"Main Camera","_parent":{"__id__":2},"_components":[{"__type__":"cc.Camera","node":{"__id__":3}}]},{"__type__":"cc.Node","_name":"backGround","_parent":{"__id__":2},"_children":[{"__id__":5},{"__id__":6}],"_components":[{"__type__":"cc.Sprite","node":{"__id__":4},"_spriteFrame":{"__uuid__":"37w4C/N35KUKWh+JXUhBiU"}}],"_contentSize":{"__type__":"cc.Size","width":640,"height":960}},{"__type__":"cc.Node","_name":"title","_parent":{"__id__":4},"_components":[{"__type__":"cc.Sprite","node":{"__id__":5},"_spriteFrame":{"__uuid__":"74c16z311HS6BSlDaaHopu"}}],"_contentSize":{"__type__":"cc.Size","width":576,"height":391},"_position":{"__type__":"cc.Vec2","y":235}},{"__type__":"cc.Node","_name":"start_1","_parent":{"__id__":4},"_components":[{"__type__":"cc.Sprite","node":{"__id__":6},"_spriteFrame":{"__uuid__":"47w75UvYFNI4iuv6AkEtIi"}},{"__type__":"cc.Animation","node":{"__id__":6},"_defaultClip":{"__uuid__":"60WGn/oRFO4baRZKko6wbv"},"_clips":[{"__uuid__":"60WGn/oRFO4baRZKko6wbv"}],"playOnLoad":true}],"_contentSize":{"__type__":"cc.Size","width":295,"height":87}}],{"__type__":"cc.SpriteFrame","content":{"name":"indexBg","texture":"26aTDt18FLpKsbgyJcL+9n","rect":[0,0,640,960],"offset":[0,0],"originalSize":[640,960]}},{"__type__":"cc.SpriteFrame","content":{"name":"start_1","texture":"83GEtdbZJIyKYoNkamryRW","rect":[0,0,295,87],"offset":[0,0],"originalSize":[295,87]}},{"__type__":"cc.AnimationClip","_name":"scale","_duration":0.3333333333333333,"speed":0.5,"wrapMode":"54","curveData":{"props":{"scale":[{"frame":0,"value":{"__type__":"cc.Vec2","x":1,"y":1}},{"frame":0.16666666666666666,"value":{"__type__":"cc.Vec2","x":1.1,"y":1.1}},{"frame":0.3333333333333333,"value":{"__type__":"cc.Vec2","x":1,"y":1}}]}}},{"__type__":"cc.SpriteFrame","content":{"name":"title","texture":"65Gk/TB+FC2q/Rq/oOFnwF","rect":[0,0,576,391],"offset":[0,0],"originalSize":[576,391]}}]